swarmauri_middleware_bulkhead/BulkheadMiddleware.py
swarmauri_middleware_bulkhead/__init__.py
swarmauri_middleware_bulkhead-0.8.0.dev4.dist-info/LICENSE
swarmauri_middleware_bulkhead-0.8.0.dev4.dist-info/METADATA
swarmauri_middleware_bulkhead-0.8.0.dev4.dist-info/WHEEL
swarmauri_middleware_bulkhead-0.8.0.dev4.dist-info/entry_points.txt
swarmauri_middleware_bulkhead-0.8.0.dev4.dist-info/RECORD
